laceworksdk/__init__.py
laceworksdk/api/__init__.py
laceworksdk/api/base_endpoint.py
laceworksdk/api/crud_endpoint.py
laceworksdk/api/read_endpoint.py
laceworksdk/api/search_endpoint.py
laceworksdk/api/v2/__init__.py
laceworksdk/api/v2/activities.py
laceworksdk/api/v2/agent_access_tokens.py
laceworksdk/api/v2/agent_info.py
laceworksdk/api/v2/alert_channels.py
laceworksdk/api/v2/alert_profiles.py
laceworksdk/api/v2/alert_rules.py
laceworksdk/api/v2/alerts.py
laceworksdk/api/v2/audit_logs.py
laceworksdk/api/v2/cloud_accounts.py
laceworksdk/api/v2/cloud_activities.py
laceworksdk/api/v2/configs.py
laceworksdk/api/v2/container_registries.py
laceworksdk/api/v2/contract_info.py
laceworksdk/api/v2/data_export_rules.py
laceworksdk/api/v2/datasources.py
laceworksdk/api/v2/entities.py
laceworksdk/api/v2/events.py
laceworksdk/api/v2/inventory.py
laceworksdk/api/v2/organization_info.py
laceworksdk/api/v2/policies.py
laceworksdk/api/v2/policy_exceptions.py
laceworksdk/api/v2/queries.py
laceworksdk/api/v2/report_definitions.py
laceworksdk/api/v2/report_rules.py
laceworksdk/api/v2/reports.py
laceworksdk/api/v2/resource_groups.py
laceworksdk/api/v2/schemas.py
laceworksdk/api/v2/team_members.py
laceworksdk/api/v2/team_users.py
laceworksdk/api/v2/user_groups.py
laceworksdk/api/v2/user_profile.py
laceworksdk/api/v2/vulnerabilities.py
laceworksdk/api/v2/vulnerability_exceptions.py
laceworksdk/api/v2/vulnerability_policies.py
laceworksdk/config.py
laceworksdk/exceptions.py
laceworksdk/http_session.py
laceworksdk-4.1.0.dist-info/LICENSE
laceworksdk-4.1.0.dist-info/METADATA
laceworksdk-4.1.0.dist-info/WHEEL
laceworksdk-4.1.0.dist-info/RECORD
