Metadata-Version: 2.1
Name: laceworksdk
Version: 4.1.0
Summary: Community-developed Python SDK for the Lacework APIs
Home-page: https://github.com/lacework/python-sdk
License: MIT
Keywords: lacework,api,sdk,python
Author: Lacework
Maintainer: Tim MacDonald
Maintainer-email: tim.macdonald@lacework.net
Requires-Python: >=3.8,<4
Classifier: Development Status :: 4 - Beta
Classifier: Intended Audience :: Developers
Classifier: License :: OSI Approved :: MIT License
Classifier: Programming Language :: Python :: 3
Classifier: Programming Language :: Python :: 3.8
Classifier: Programming Language :: Python :: 3.9
Classifier: Programming Language :: Python :: 3.10
Classifier: Programming Language :: Python :: 3.11
Classifier: Programming Language :: Python :: 3.12
Classifier: Topic :: Software Development :: Build Tools
Requires-Dist: bleach (>=4.1.0)
Requires-Dist: configparser (>=5.2.0)
Requires-Dist: importlib-metadata (>=4.2)
Requires-Dist: python-dotenv (>=0.20.0)
Requires-Dist: requests (>=2.27.1)
Requires-Dist: urllib3 (>=1.26.15)
Project-URL: Repository, https://github.com/lacework/python-sdk
